quickmp/__init__.py
quickmp/_quickmp.cpython-311-x86_64-linux-gnu.so
quickmp/_version.py
quickmp-0.1.0.dist-info/METADATA
quickmp-0.1.0.dist-info/WHEEL
quickmp-0.1.0.dist-info/RECORD
quickmp-0.1.0.dist-info/licenses/LICENSE
