Metadata-Version: 2.4
Name: quickmp
Version: 0.1.0
Summary: Quickly compute matrix profiles
Author-Email: Keichi Takahashi <hello@keichi.dev>
License-Expression: MIT
Classifier: Programming Language :: C++
Classifier: Programming Language :: Python
Classifier: Operating System :: MacOS :: MacOS X
Classifier: Operating System :: POSIX :: Linux
Classifier: Development Status :: 3 - Alpha
Classifier: Intended Audience :: Science/Research
Classifier: Topic :: Scientific/Engineering :: Mathematics
Requires-Python: >=3.9
Requires-Dist: numpy>=1.24.0
Provides-Extra: test
Requires-Dist: pytest>=8.3.0; extra == "test"
Requires-Dist: stumpy>=1.13.0; extra == "test"
